NiukeWangMingqiXiaozhaoBishiZhentiJingxuanChanpinYunyingYouxiCehuaPian20202021/README.md
NiukeWangMingqiXiaozhaoBishiZhentiJingxuanChanpinYunyingYouxiCehuaPian20202021/__init__.py
NiukeWangMingqiXiaozhaoBishiZhentiJingxuanChanpinYunyingYouxiCehuaPian20202021/__main__.py
NiukeWangMingqiXiaozhaoBishiZhentiJingxuanChanpinYunyingYouxiCehuaPian20202021/file.epub
NiukeWangMingqiXiaozhaoBishiZhentiJingxuanChanpinYunyingYouxiCehuaPian20202021/index.html
NiukeWangMingqiXiaozhaoBishiZhentiJingxuanChanpinYunyingYouxiCehuaPian20202021/css/__init__.py
NiukeWangMingqiXiaozhaoBishiZhentiJingxuanChanpinYunyingYouxiCehuaPian20202021/css/annotations.css
NiukeWangMingqiXiaozhaoBishiZhentiJingxuanChanpinYunyingYouxiCehuaPian20202021/css/main.css
NiukeWangMingqiXiaozhaoBishiZhentiJingxuanChanpinYunyingYouxiCehuaPian20202021/css/normalize.css
NiukeWangMingqiXiaozhaoBishiZhentiJingxuanChanpinYunyingYouxiCehuaPian20202021/css/popup.css
NiukeWangMingqiXiaozhaoBishiZhentiJingxuanChanpinYunyingYouxiCehuaPian20202021/font/__init__.py
NiukeWangMingqiXiaozhaoBishiZhentiJingxuanChanpinYunyingYouxiCehuaPian20202021/font/fontello.eot
NiukeWangMingqiXiaozhaoBishiZhentiJingxuanChanpinYunyingYouxiCehuaPian20202021/font/fontello.svg
NiukeWangMingqiXiaozhaoBishiZhentiJingxuanChanpinYunyingYouxiCehuaPian20202021/font/fontello.ttf
NiukeWangMingqiXiaozhaoBishiZhentiJingxuanChanpinYunyingYouxiCehuaPian20202021/font/fontello.woff
NiukeWangMingqiXiaozhaoBishiZhentiJingxuanChanpinYunyingYouxiCehuaPian20202021/img/__init__.py
NiukeWangMingqiXiaozhaoBishiZhentiJingxuanChanpinYunyingYouxiCehuaPian20202021/img/annotator-glyph-sprite.png
NiukeWangMingqiXiaozhaoBishiZhentiJingxuanChanpinYunyingYouxiCehuaPian20202021/img/annotator-icon-sprite.png
NiukeWangMingqiXiaozhaoBishiZhentiJingxuanChanpinYunyingYouxiCehuaPian20202021/img/apple-touch-icon.png
NiukeWangMingqiXiaozhaoBishiZhentiJingxuanChanpinYunyingYouxiCehuaPian20202021/img/cancelfullscreen.png
niuke_wang_mingqi_xiaozhao_bishi_zhenti_jingxuan_chanpin_yunying_youxi_cehua_pian_2020_2021-2024.3.5.0.dist-info/METADATA
niuke_wang_mingqi_xiaozhao_bishi_zhenti_jingxuan_chanpin_yunying_youxi_cehua_pian_2020_2021-2024.3.5.0.dist-info/WHEEL
niuke_wang_mingqi_xiaozhao_bishi_zhenti_jingxuan_chanpin_yunying_youxi_cehua_pian_2020_2021-2024.3.5.0.dist-info/entry_points.txt
niuke_wang_mingqi_xiaozhao_bishi_zhenti_jingxuan_chanpin_yunying_youxi_cehua_pian_2020_2021-2024.3.5.0.dist-info/top_level.txt
niuke_wang_mingqi_xiaozhao_bishi_zhenti_jingxuan_chanpin_yunying_youxi_cehua_pian_2020_2021-2024.3.5.0.dist-info/RECORD
